mentionkit/__init__.py
mentionkit/normalize.py
mentionkit/parse.py
mentionkit/summarize.py
mentionkit/types.py
mentionkit/validate.py
mentionkit-0.2.2.dist-info/METADATA
mentionkit-0.2.2.dist-info/WHEEL
mentionkit-0.2.2.dist-info/RECORD
